replicantdrivesim/__init__.py
replicantdrivesim/replicantdrivesim.so
replicantdrivesim/Builds/StandaloneOSX/libReplicantDriveSim.app/Contents/Info.plist
replicantdrivesim/Builds/StandaloneOSX/libReplicantDriveSim.app/Contents/Frameworks/UnityPlayer.dylib
replicantdrivesim/Builds/StandaloneOSX/libReplicantDriveSim.app/Contents/Frameworks/libMonoPosixHelper.dylib
replicantdrivesim/Builds/StandaloneOSX/libReplicantDriveSim.app/Contents/Frameworks/libmono-native.dylib
replicantdrivesim/Builds/StandaloneOSX/libReplicantDriveSim.app/Contents/Frameworks/libmonobdwgc-2.0.dylib
replicantdrivesim/Builds/StandaloneOSX/libReplicantDriveSim.app/Contents/MacOS/UnityReplicantDriveSim
replicantdrivesim/Builds/StandaloneOSX/libReplicantDriveSim.app/Contents/MonoBleedingEdge/etc/mono/browscap.ini
replicantdrivesim/Builds/StandaloneOSX/libReplicantDriveSim.app/Contents/MonoBleedingEdge/etc/mono/config
replicantdrivesim/Builds/StandaloneOSX/libReplicantDriveSim.app/Contents/MonoBleedingEdge/etc/mono/2.0/DefaultWsdlHelpGenerator.aspx
replicantdrivesim/Builds/StandaloneOSX/libReplicantDriveSim.app/Contents/MonoBleedingEdge/etc/mono/2.0/machine.config
replicantdrivesim/Builds/StandaloneOSX/libReplicantDriveSim.app/Contents/MonoBleedingEdge/etc/mono/2.0/settings.map
replicantdrivesim/Builds/StandaloneOSX/libReplicantDriveSim.app/Contents/MonoBleedingEdge/etc/mono/2.0/web.config
replicantdrivesim/Builds/StandaloneOSX/libReplicantDriveSim.app/Contents/MonoBleedingEdge/etc/mono/2.0/Browsers/Compat.browser
replicantdrivesim/Builds/StandaloneOSX/libReplicantDriveSim.app/Contents/MonoBleedingEdge/etc/mono/4.0/DefaultWsdlHelpGenerator.aspx
replicantdrivesim/Builds/StandaloneOSX/libReplicantDriveSim.app/Contents/MonoBleedingEdge/etc/mono/4.0/machine.config
replicantdrivesim/Builds/StandaloneOSX/libReplicantDriveSim.app/Contents/MonoBleedingEdge/etc/mono/4.0/settings.map
replicantdrivesim/Builds/StandaloneOSX/libReplicantDriveSim.app/Contents/MonoBleedingEdge/etc/mono/4.0/web.config
replicantdrivesim-0.6.5.dist-info/LICENSE
replicantdrivesim-0.6.5.dist-info/METADATA
replicantdrivesim-0.6.5.dist-info/WHEEL
replicantdrivesim-0.6.5.dist-info/entry_points.txt
replicantdrivesim-0.6.5.dist-info/top_level.txt
replicantdrivesim-0.6.5.dist-info/RECORD
