Metadata-Version: 2.1
Name: replicantdrivesim
Version: 0.6.5
Summary: A Unity Traffic Simulation
Home-page: https://chrisjcc.github.io/ReplicantDriveSim
Author: Christian Contreras Campana
Author-email: chrisjcc.physics@gmail.com
License: MIT
Keywords: traffic,simulation,autonomous driving,reinforcement learning,multi-agent reinforcement learning,rl,marl
Classifier: Development Status :: 3 - Alpha
Classifier: Intended Audience :: Science/Research
Classifier: Topic :: Scientific/Engineering :: Artificial Intelligence
Classifier: Programming Language :: Python :: 3
Classifier: License :: OSI Approved :: MIT License
Classifier: Operating System :: OS Independent
License-File: LICENSE
Requires-Dist: protobuf==3.20.2
